SimpleSys/SimpleSys.py
SimpleSys/__init__.py
SimpleSystem-1.0.dist-info/LICENSE.txt
SimpleSystem-1.0.dist-info/METADATA
SimpleSystem-1.0.dist-info/WHEEL
SimpleSystem-1.0.dist-info/top_level.txt
SimpleSystem-1.0.dist-info/RECORD
