Metadata-Version: 2.1
Name: SimpleSystem
Version: 1.0
Summary: A module used to view the system information in a simple way.
Author: Daniel Drury
Author-email: daniel-drury@outlook.com
Classifier: Programming Language :: Python :: 3
Classifier: License :: OSI Approved :: MIT License
Classifier: Operating System :: OS Independent
Requires-Python: >=3.6
License-File: LICENSE.txt
